describecsv/__init__.py
describecsv/describecsv.py
describecsv_nc-0.1.0.dist-info/METADATA
describecsv_nc-0.1.0.dist-info/WHEEL
describecsv_nc-0.1.0.dist-info/entry_points.txt
describecsv_nc-0.1.0.dist-info/licenses/LICENSE
describecsv_nc-0.1.0.dist-info/RECORD
