Metadata-Version: 2.4
Name: describecsv-nc
Version: 0.1.0
Summary: A tool for analyzing and describing CSV files
Project-URL: Homepage, https://github.com/nealcaren/describecsv
Project-URL: Bug Tracker, https://github.com/nealcaren/describecsv/issues
Author-email: Neal Caren <neal.caren@unc.edu>
License-File: LICENSE
Classifier: License :: OSI Approved :: MIT License
Classifier: Operating System :: OS Independent
Classifier: Programming Language :: Python :: 3
Requires-Python: >=3.10
Requires-Dist: chardet>=5.0.0
Requires-Dist: numpy>=1.24.0
Requires-Dist: pandas>=2.0.0
Requires-Dist: python-dateutil>=2.8.0
Requires-Dist: pytz>=2023.3
Requires-Dist: tqdm>=4.65.0
Requires-Dist: tzdata>=2023.3
